roboflowoak/__init__.py
roboflowoak/api.py
roboflowoak/pipe.py
roboflowoak/postprocs.py
roboflowoak-0.0.12.dist-info/LICENSE
roboflowoak-0.0.12.dist-info/METADATA
roboflowoak-0.0.12.dist-info/WHEEL
roboflowoak-0.0.12.dist-info/top_level.txt
roboflowoak-0.0.12.dist-info/RECORD
