Metadata-Version: 2.1
Name: roboflowoak
Version: 0.0.12
Summary: python client for deploying Roboflow models to OAK devices
Home-page: https://www.roboflow.com
Author: Roboflow
Author-email: jacob@roboflow.com
License: GPLv3+
Classifier: Programming Language :: Python :: 3
Classifier: Operating System :: OS Independent
Requires-Python: >=3.6
License-File: LICENSE
Requires-Dist: requests (==2.26.0)
